{
  "project_info": {
    "project_number": "92721221789",
    "firebase_url": "https://midterm01-mariami-chakhvadze.firebaseio.com",
    "project_id": "midterm01-mariami-chakhvadze",
    "storage_bucket": "midterm01-mariami-chakhvadze.appspot.com"
  },
  "client": [
    {
      "client_info": {
        "mobilesdk_app_id": "1:92721221789:android:8f5bfd1296c4d9be840474",
        "android_client_info": {
          "package_name": "com.example.midterm01mariamichakhvadze"
        }
      },
      "oauth_client": [
        {
          "client_id": "92721221789-frpppvf5sg1md7iibq1q4134ouvln3dq.apps.googleusercontent.com",
          "client_type": 3
        }
      ],
      "api_key": [
        {
          "current_key": "AIzaSyAStHa7EliPlR5xoVbm1twORQsi22se3pQ"
        }
      ],
      "services": {
        "appinvite_service": {
          "other_platform_oauth_client": [
            {
              "client_id": "92721221789-frpppvf5sg1md7iibq1q4134ouvln3dq.apps.googleusercontent.com",
              "client_type": 3
            }
          ]
        }
      }
    }
  ],
  "configuration_version": "1"
}